std/README_template.md
std/__init__.py
std/config.py
std/example_database_structure.sql
std/template_admin_window.py
std/template_client_window.py
std/template_db.py
std/template_login_window.py
std/template_main.py
std/template_manager_window.py
std/examples/README.md
std/examples/__init__.py
std/examples/admin_window.py
std/examples/client_window.py
std/examples/db.py
std/examples/login_window.py
std/examples/main.py
std/examples/manager_window.py
stdd-0.1.0.dist-info/licenses/LICENSE
stdd-0.1.0.dist-info/METADATA
stdd-0.1.0.dist-info/WHEEL
stdd-0.1.0.dist-info/top_level.txt
stdd-0.1.0.dist-info/RECORD
