Metadata-Version: 2.4
Name: stdd
Version: 0.1.0
Summary: Universal template for PyQt6 + PyMySQL applications with role-based access control
Home-page: https://github.com/yourusername/std
Author: Your Name
Author-email: Angelina <mayshmellina@gmail.com>
License: MIT
Project-URL: Homepage, https://github.com/LiiraGH/std
Project-URL: Documentation, https://github.com/LiiraGH/std#readme
Project-URL: Repository, https://github.com/LiiraGH/std
Project-URL: Issues, https://github.com/LiiraGH/std/issues
Keywords: pyqt6,pymysql,template,gui,database,role-based-access
Classifier: Development Status :: 3 - Alpha
Classifier: Intended Audience :: Developers
Classifier: License :: OSI Approved :: MIT License
Classifier: Programming Language :: Python :: 3
Classifier: Programming Language :: Python :: 3.8
Classifier: Programming Language :: Python :: 3.9
Classifier: Programming Language :: Python :: 3.10
Classifier: Programming Language :: Python :: 3.11
Classifier: Programming Language :: Python :: 3.12
Classifier: Topic :: Software Development :: Libraries :: Python Modules
Classifier: Topic :: Software Development :: User Interfaces
Requires-Python: >=3.8
License-File: LICENSE
Requires-Dist: PyQt6>=6.6.0
Requires-Dist: PyMySQL>=1.1.0
Provides-Extra: dev
Requires-Dist: pytest>=7.0.0; extra == "dev"
Requires-Dist: black>=23.0.0; extra == "dev"
Requires-Dist: flake8>=6.0.0; extra == "dev"
Dynamic: author
Dynamic: home-page
Dynamic: license-file
Dynamic: requires-python
